LICENSE
README.md
setup.py
ns_lattice.egg-info/PKG-INFO
ns_lattice.egg-info/SOURCES.txt
ns_lattice.egg-info/dependency_links.txt
ns_lattice.egg-info/entry_points.txt
ns_lattice.egg-info/not-zip-safe
ns_lattice.egg-info/requires.txt
ns_lattice.egg-info/top_level.txt
src/ns_lattice/__init__.py
src/ns_lattice/__main__.py
src/ns_lattice/class_div.py
src/ns_lattice/class_dp_lattice.py
src/ns_lattice/class_eta.py
src/ns_lattice/class_ns_tools.py
src/ns_lattice/convert_to_tex.py
src/ns_lattice/div_in_lattice.py
src/ns_lattice/dp_involutions.py
src/ns_lattice/dp_root_bases.py
src/ns_lattice/ns_basis.py
src/ns_lattice/ns_tools.sobj
src/ns_lattice/reducible_conics.py
src/ns_lattice/sage_interface.py
src/tests/__init__.py
src/tests/test_class_div.py
src/tests/test_class_dp_lattice.py
src/tests/test_class_eta.py
src/tests/test_class_ns_tools.py
src/tests/test_convert_to_tex.py
src/tests/test_div_in_lattice.py
src/tests/test_dp_involutions.py
src/tests/test_dp_root_basis.py
src/tests/test_ns_basis.py